glitchlings/__init__.py
glitchlings/__main__.py
glitchlings/_corruption_engine.cp313-win_amd64.pyd
glitchlings/auggie.py
glitchlings/config.toml
glitchlings/constants.py
glitchlings/main.py
glitchlings/protocols.py
glitchlings/runtime_config.py
glitchlings/_corruption_engine/__init__.py
glitchlings/assets/__init__.py
glitchlings/assets/apostrofae_pairs.json
glitchlings/assets/ekkokin_homophones.json
glitchlings/assets/hokey_assets.json
glitchlings/assets/mim1c_homoglyphs.json.gz.b64
glitchlings/assets/ocr_confusions.tsv
glitchlings/assets/pipeline_assets.json
glitchlings/assets/lexemes/academic.json
glitchlings/assets/lexemes/colors.json
glitchlings/assets/lexemes/corporate.json
glitchlings/assets/lexemes/cyberpunk.json
glitchlings/assets/lexemes/lovecraftian.json
glitchlings/assets/lexemes/synonyms.json
glitchlings/attack/__init__.py
glitchlings/attack/analysis.py
glitchlings/attack/core.py
glitchlings/attack/core_execution.py
glitchlings/attack/core_planning.py
glitchlings/attack/encode.py
glitchlings/attack/metrics.py
glitchlings/attack/metrics_dispatch.py
glitchlings/attack/tokenization.py
glitchlings/attack/tokenizer_metrics.py
glitchlings/compat/__init__.py
glitchlings/compat/loaders.py
glitchlings/compat/types.py
glitchlings/conf/__init__.py
glitchlings/conf/loaders.py
glitchlings/conf/schema.py
glitchlings/conf/types.py
glitchlings/dev/__init__.py
glitchlings/dev/docs.py
glitchlings/dlc/__init__.py
glitchlings/dlc/_shared.py
glitchlings/dlc/gutenberg.py
glitchlings/dlc/huggingface.py
glitchlings/dlc/langchain.py
glitchlings/dlc/nemo.py
glitchlings/dlc/prime.py
glitchlings/dlc/pytorch.py
glitchlings/dlc/pytorch_lightning.py
glitchlings/internal/__init__.py
glitchlings/internal/rust.py
glitchlings/internal/rust_ffi.py
glitchlings/util/__init__.py
glitchlings/util/adapters.py
glitchlings/util/keyboards.py
glitchlings/util/transcripts.py
glitchlings/zoo/__init__.py
glitchlings/zoo/core.py
glitchlings/zoo/core_execution.py
glitchlings/zoo/core_planning.py
glitchlings-1.0.0.dist-info/licenses/LICENSE
glitchlings-1.0.0.dist-info/METADATA
glitchlings-1.0.0.dist-info/WHEEL
glitchlings-1.0.0.dist-info/entry_points.txt
glitchlings-1.0.0.dist-info/top_level.txt
glitchlings-1.0.0.dist-info/RECORD
