Metadata-Version: 2.4
Name: glitchlings
Version: 1.0.0
Summary: Deterministic, high performance, principled natural language augmentation.
Author: osoleve
License-Expression: Apache-2.0
Project-URL: Homepage, https://github.com/osoleve/glitchlings
Project-URL: Repository, https://github.com/osoleve/glitchlings.git
Project-URL: Issues, https://github.com/osoleve/glitchlings/issues
Project-URL: Changelog, https://github.com/osoleve/glitchlings/releases
Keywords: nlp,adversarial augmentation,text augmentation,data augmentation,domain randomization,tokenizer,tokenization,robustness
Classifier: Development Status :: 5 - Production/Stable
Classifier: Intended Audience :: Developers
Classifier: Programming Language :: Python
Classifier: Programming Language :: Python :: 3
Classifier: Programming Language :: Python :: 3.10
Classifier: Programming Language :: Python :: 3.11
Classifier: Programming Language :: Python :: 3.12
Classifier: Programming Language :: Python :: 3.13
Classifier: Programming Language :: Rust
Classifier: Topic :: Scientific/Engineering :: Artificial Intelligence
Classifier: Topic :: Software Development :: Testing
Requires-Python: >=3.10
License-File: LICENSE
Requires-Dist: tomli>=2.0.1; python_version < "3.11"
Requires-Dist: importlib-resources>=5.0.0; python_version < "3.11"
Requires-Dist: packaging>=23.0
Requires-Dist: pyyaml>=6.0.0
Provides-Extra: all
Requires-Dist: hypothesis>=6.140.0; extra == "all"
Requires-Dist: interrogate>=1.5.0; extra == "all"
Requires-Dist: jellyfish==1.2.0; extra == "all"
Requires-Dist: langchain-core>=0.3.0; extra == "all"
Requires-Dist: mkdocs>=1.6.0; extra == "all"
Requires-Dist: mkdocs-material>=9.5.0; extra == "all"
Requires-Dist: mkdocstrings[python]>=0.24.0; extra == "all"
Requires-Dist: mkdocstrings-python>=1.10.0; extra == "all"
Requires-Dist: mypy>=1.8.0; extra == "all"
Requires-Dist: numpy<3.0,>=1.24; extra == "all"
Requires-Dist: pre-commit>=3.8.0; extra == "all"
Requires-Dist: py-gutenberg==1.0.0; extra == "all"
Requires-Dist: pytest>=8.0.0; extra == "all"
Requires-Dist: pytest-cov>=4.1.0; extra == "all"
Requires-Dist: ruff>=0.6.0; extra == "all"
Requires-Dist: types-PyYAML>=6.0.0; extra == "all"
Requires-Dist: verifiers>=0.1.8; extra == "all"
Requires-Dist: tiktoken>=0.3.0; extra == "all"
Requires-Dist: tokenizers>=0.13.0; extra == "all"
Provides-Extra: tok
Requires-Dist: tiktoken>=0.3.0; extra == "tok"
Requires-Dist: tokenizers>=0.13.0; extra == "tok"
Provides-Extra: gutenberg
Requires-Dist: py-gutenberg==1.0.0; extra == "gutenberg"
Provides-Extra: hf
Requires-Dist: datasets>=4.0.0; extra == "hf"
Provides-Extra: lightning
Requires-Dist: pytorch_lightning>=2.0.0; extra == "lightning"
Provides-Extra: langchain
Requires-Dist: langchain-core>=0.3.0; extra == "langchain"
Provides-Extra: prime
Requires-Dist: verifiers>=0.1.8; extra == "prime"
Requires-Dist: jellyfish==1.2.0; extra == "prime"
Provides-Extra: torch
Requires-Dist: torch>=2.0.0; extra == "torch"
Provides-Extra: dev
Requires-Dist: pytest>=8.0.0; extra == "dev"
Requires-Dist: pytest-cov>=4.1.0; extra == "dev"
Requires-Dist: hypothesis>=6.140.0; extra == "dev"
Requires-Dist: numpy<3.0,>=1.24; extra == "dev"
Requires-Dist: mkdocs>=1.6.0; extra == "dev"
Requires-Dist: mkdocstrings[python]>=0.24.0; extra == "dev"
Requires-Dist: mkdocs-material>=9.5.0; extra == "dev"
Requires-Dist: mkdocstrings-python>=1.10.0; extra == "dev"
Requires-Dist: interrogate>=1.5.0; extra == "dev"
Requires-Dist: ruff>=0.6.0; extra == "dev"
Requires-Dist: mypy>=1.8.0; extra == "dev"
Requires-Dist: pre-commit>=3.8.0; extra == "dev"
Requires-Dist: types-PyYAML>=6.0.0; extra == "dev"
Dynamic: license-file
